aika/__init__.py
aika/arbitrary_dateparser.py
aika/core.py
aika/dateparser_german.py
aika/daterangeparser_german.py
aika/model.py
aika/util.py
aika-0.3.1.dist-info/licenses/LICENSE
aika-0.3.1.dist-info/METADATA
aika-0.3.1.dist-info/WHEEL
aika-0.3.1.dist-info/top_level.txt
aika-0.3.1.dist-info/RECORD
