Metadata-Version: 2.4
Name: aika
Version: 0.3.1
Summary: Time interval parsing utilities for multiple languages.
Author-email: Andreas Motl <andreas.motl@panodata.org>, Richard Pobering <richard.pobering@panodata.org>
License: LGPL 3, EUPL 1.2
Project-URL: Changelog, https://github.com/panodata/aika/blob/main/CHANGES.md
Project-URL: Issues, https://github.com/panodata/aika/issues
Project-URL: Repository, https://github.com/panodata/aika
Keywords: date parsing,multi-language,time,time interval,time range,utility
Classifier: Development Status :: 3 - Alpha
Classifier: Environment :: Console
Classifier: Environment :: Web Environment
Classifier: Intended Audience :: Customer Service
Classifier: Intended Audience :: Developers
Classifier: Intended Audience :: Education
Classifier: Intended Audience :: Information Technology
Classifier: Intended Audience :: Telecommunications Industry
Classifier: License :: OSI Approved :: European Union Public Licence 1.2 (EUPL 1.2)
Classifier: License :: OSI Approved :: GNU Lesser General Public License v3 (LGPLv3)
Classifier: Operating System :: MacOS :: MacOS X
Classifier: Operating System :: POSIX :: Linux
Classifier: Operating System :: Unix
Classifier: Programming Language :: Python
Classifier: Programming Language :: Python :: 3 :: Only
Classifier: Programming Language :: Python :: 3.8
Classifier: Programming Language :: Python :: 3.9
Classifier: Programming Language :: Python :: 3.10
Classifier: Programming Language :: Python :: 3.11
Classifier: Programming Language :: Python :: 3.12
Classifier: Programming Language :: Python :: 3.13
Classifier: Programming Language :: Python :: 3.14
Classifier: Topic :: Communications
Classifier: Topic :: Education
Classifier: Topic :: Home Automation
Classifier: Topic :: Software Development :: Libraries
Classifier: Topic :: Utilities
Requires-Python: >=3.8
License-File: LICENSE
Requires-Dist: dateparser<1.3
Requires-Dist: daterangeparser<1.4
Requires-Dist: fiscalyear<0.5
Requires-Dist: pendulum<4
Requires-Dist: python-dateutil<3
Provides-Extra: develop
Requires-Dist: mypy<1.20; extra == "develop"
Requires-Dist: poethepoet<1; extra == "develop"
Requires-Dist: pyproject-fmt<3; extra == "develop"
Requires-Dist: ruff<0.15; extra == "develop"
Requires-Dist: validate-pyproject<1; extra == "develop"
Provides-Extra: release
Requires-Dist: build<2; extra == "release"
Requires-Dist: twine<7; extra == "release"
Provides-Extra: test
Requires-Dist: freezegun<1.6; extra == "test"
Requires-Dist: pytest<10; extra == "test"
Requires-Dist: pytest-cov<8; extra == "test"
Dynamic: license-file
